LICENSE.rst
MANIFEST.in
README.rst
REQUIREMENTS
setup.py
django_flux.egg-info/PKG-INFO
django_flux.egg-info/SOURCES.txt
django_flux.egg-info/dependency_links.txt
django_flux.egg-info/requires.txt
django_flux.egg-info/top_level.txt
flux/__init__.py
flux/admin.py
flux/models.py
flux/tests.py
flux/urls.py
flux/utils.py
flux/views.py
flux/conf/__init__.py
flux/conf/settings.py
flux/fixtures/test_data.json
flux/management/__init__.py
flux/management/commands/__init__.py
flux/management/commands/update_flux.py
flux/static/flux/css/account_index.css
flux/static/flux/css/bar_mouseover_labels.css
flux/static/flux/css/sparkline.css
flux/static/flux/css/timeseries.css
flux/static/flux/js/bar_mouseover_labels.js
flux/static/flux/js/sparkline.js
flux/static/flux/js/sparkline_mouseover_labels.js
flux/templates/flux/account_detail.html
flux/templates/flux/account_index.html
flux/templates/flux/base.html
flux/templates/flux/timeseries.html
flux/templatetags/__init__.py
flux/templatetags/flux.py