Metadata-Version: 1.1
Name: django-flux
Version: 0.3.0
Summary: locally fetch, store, and present social media flux
Home-page: http://github.com/datascopeanalytics/django-flux
Author: Dean Malmgren
Author-email: dean.malmgren@datascopeanalytics.com
License: MIT, see LICENSE.rst
Download-URL: http://github.com/datascopeanalytics/django-flux/archives/master
Platform: UNKNOWN
